{
  "openapi": "3.0.4",
  "info": {
    "title": "GeoLocation Lookup API V1 (1.0)",
    "description": "GeoLocation Lookup API V1 1.0",
    "version": "1.0"
  },
  "paths": {
    "/api/v1/lookup/{hostname}": {
      "get": {
        "tags": [
          "GeoLookup"
        ],
        "parameters": [
          {
            "name": "hostname",
            "in": "path",
            "required": true,
            "schema": {
              "type": "string"
            }
          }
        ],
        "responses": {
          "200": {
            "description": "OK"
          }
        }
      },
      "delete": {
        "tags": [
          "GeoLookup"
        ],
        "parameters": [
          {
            "name": "hostname",
            "in": "path",
            "required": true,
            "schema": {
              "type": "string"
            }
          }
        ],
        "responses": {
          "200": {
            "description": "OK"
          }
        }
      }
    },
    "/api/v1/lookup": {
      "post": {
        "tags": [
          "GeoLookup"
        ],
        "responses": {
          "200": {
            "description": "OK"
          }
        }
      }
    }
  },
  "components": {
    "securitySchemes": {
      "Bearer": {
        "type": "apiKey",
        "description": "",
        "name": "Authorization",
        "in": "header"
      }
    }
  },
  "security": [
    {
      "Bearer": [ ]
    }
  ]
}
